stockfish_wannabe/__init__.py
stockfish_wannabe/stockfish_wannabe.py
stockfish_wannabe-0.1.1.dist-info/METADATA
stockfish_wannabe-0.1.1.dist-info/WHEEL
stockfish_wannabe-0.1.1.dist-info/top_level.txt
stockfish_wannabe-0.1.1.dist-info/RECORD
